MANIFEST.in
README.rst
runaudman
setup.cfg
setup.py
audman/__init__.py
audman/aud_dbus.py
audman/audws.py
audman/favicon.ico
audman/ic_arrow_drop_down_black_24dp.png
audman/ic_arrow_drop_up_black_24dp.png
audman/ic_fast_forward_black_48dp.png
audman/ic_fast_rewind_black_48dp.png
audman/ic_pause_black_48dp.png
audman/ic_play_arrow_black_48dp.png
audman/ic_repeat_black_48dp.png
audman/ic_shuffle_black_48dp.png
audman/ic_skip_next_black_48dp.png
audman/ic_skip_previous_black_48dp.png
audman/ic_stop_black_48dp.png
audman/ic_unfold_less_black_24dp.png
audman/ic_unfold_more_black_24dp.png
audman/ic_vertical_align_center_black_24dp.png
audman/ic_volume_down_black_48dp.png
audman/ic_volume_up_black_48dp.png
audman.egg-info/PKG-INFO
audman.egg-info/SOURCES.txt
audman.egg-info/dependency_links.txt
audman.egg-info/requires.txt
audman.egg-info/top_level.txt